mango_autoencoder/__init__.py
mango_autoencoder/autoencoder.py
mango_autoencoder/logging/__init__.py
mango_autoencoder/logging/logger.py
mango_autoencoder/modules/__init__.py
mango_autoencoder/modules/anomaly_detector.py
mango_autoencoder/modules/decoder.py
mango_autoencoder/modules/encoder.py
mango_autoencoder/tests/__init__.py
mango_autoencoder/tests/test_autoencoder.py
mango_autoencoder/utils/__init__.py
mango_autoencoder/utils/plots.py
mango_autoencoder/utils/processing.py
mango_autoencoder/utils/sequences.py
mango_autoencoder-1.0.1.dist-info/licenses/LICENSE
mango_autoencoder-1.0.1.dist-info/METADATA
mango_autoencoder-1.0.1.dist-info/WHEEL
mango_autoencoder-1.0.1.dist-info/top_level.txt
mango_autoencoder-1.0.1.dist-info/RECORD
