Metadata-Version: 2.4
Name: mango-autoencoder
Version: 1.0.1
Summary: Library with a collection of useful classes and methods to DRY
Author-email: baobab soluciones <mango@baobabsoluciones.es>
License: Apache Software License
Project-URL: repository, https://github.com/baobabsoluciones/mango
Classifier: Programming Language :: Python :: 3.11
Classifier: License :: OSI Approved :: Apache Software License
Classifier: Operating System :: OS Independent
Classifier: Development Status :: 4 - Beta
Requires-Python: <3.12,>=3.11
License-File: LICENSE
Requires-Dist: mango<2.0.0,>=1.0.0
Requires-Dist: pandas<3.0.0,>=2.0.3
Requires-Dist: plotly>=6.2.0
Requires-Dist: polars>=1.31.0
Requires-Dist: scikit-learn>=1.6.1
Requires-Dist: tensorflow==2.18.0
Requires-Dist: tensorflow-io-gcs-filesystem==0.31.0
Provides-Extra: dev
Requires-Dist: coverage[toml]>=7.0; extra == "dev"
Dynamic: license-file
